gqlspection/GQLArg.py
gqlspection/GQLEnum.py
gqlspection/GQLField.py
gqlspection/GQLList.py
gqlspection/GQLQuery.py
gqlspection/GQLSchema.py
gqlspection/GQLSubQuery.py
gqlspection/GQLType.py
gqlspection/GQLTypeKind.py
gqlspection/GQLTypeProxy.py
gqlspection/GQLWrappers.py
gqlspection/Logger.py
gqlspection/__init__.py
gqlspection/cli.py
gqlspection/introspection_query.py
gqlspection/utils.py
gqlspection-0.2.3.dist-info/LICENSE
gqlspection-0.2.3.dist-info/METADATA
gqlspection-0.2.3.dist-info/WHEEL
gqlspection-0.2.3.dist-info/entry_points.txt
gqlspection-0.2.3.dist-info/top_level.txt
gqlspection-0.2.3.dist-info/RECORD
