Metadata-Version: 2.1
Name: gqlspection
Version: 0.2.3
Summary: GraphQL Introspection parsing and query generation
Home-page: https://github.com/doyensec/gqlspection
Author: Andrew Konstantinov
Author-email: andrew@doyensec.com
Project-URL: Source, https://github.com/doyensec/gqlspection
Project-URL: Bug Reports, https://github.com/doyensec/gqlspection/issues
Project-URL: Doyensec Research, https://www.doyensec.com/research.html
Keywords: graphql,introspection
Classifier: Development Status :: 3 - Alpha
Classifier: Intended Audience :: Developers
Classifier: Intended Audience :: Information Technology
Classifier: Intended Audience :: System Administrators
Classifier: Environment :: Console
Classifier: Programming Language :: Python :: 2.7
Classifier: Programming Language :: Python :: 3
Classifier: Programming Language :: Python :: 3.7
Classifier: Programming Language :: Python :: 3.8
Classifier: Programming Language :: Python :: 3.9
Classifier: Programming Language :: Python :: 3.10
Classifier: Programming Language :: Python :: 3.11
Classifier: Programming Language :: Python :: Implementation :: CPython
Classifier: Programming Language :: Python :: Implementation :: Jython
Classifier: License :: OSI Approved :: Apache Software License
Classifier: Topic :: Software Development :: Code Generators
Classifier: Topic :: Security
Requires-Python: >=2.7
License-File: LICENSE
Requires-Dist: pathlib2 ; python_version == "2.7"
Requires-Dist: future ; python_version == "2.7"
Provides-Extra: cli
Requires-Dist: click ; extra == 'cli'
Requires-Dist: requests ; extra == 'cli'
